GeniusDeveloper/_init_.py
Hackersostt-2.0.dist-info/METADATA
Hackersostt-2.0.dist-info/WHEEL
Hackersostt-2.0.dist-info/top_level.txt
Hackersostt-2.0.dist-info/RECORD
