Metadata-Version: 2.1
Name: Hackersostt
Version: 2.0
Summary: This is text to speech package created by Himanshu
Author: Himanshu Kumar Sah
Author-email: geniusdeveloper46@gmail.com
